sarf/__init__.py
sarf/containers.py
sarf/sarf.py
sarf/notifications/__init__.py
sarf/notifications/base.py
sarf/notifications/notification.py
sarf/projects/__init__.py
sarf/projects/base.py
sarf/projects/cli.py
sarf/reports/__init__.py
sarf/reports/base.py
sarf/reports/cli.py
sarf/reports/app/__init__.py
sarf/reports/app/generator.py
sarf/reports/app/report.py
sarf/shared/__init__.py
sarf/shared/cli/__init__.py
sarf/shared/cli/crud.py
sarf/shared/cli/report_utils.py
sarf/shared/cli/forms/__init__.py
sarf/shared/cli/forms/fields.py
sarf/shared/cli/forms/form.py
sarf/shared/forms/__init__.py
sarf/shared/forms/form.py
sarf/vulnerabilities/__init__.py
sarf/vulnerabilities/base.py
sarf/vulnerabilities/cli.py
sarf-1.0.0rc2.dist-info/METADATA
sarf-1.0.0rc2.dist-info/WHEEL
sarf-1.0.0rc2.dist-info/entry_points.txt
sarf-1.0.0rc2.dist-info/top_level.txt
sarf-1.0.0rc2.dist-info/RECORD
