Metadata-Version: 2.1
Name: sarf
Version: 1.0.0rc2
Summary: SARF CLI. A security assesment tool that serves as a glue between security tools. SARF also let you write vulnerabilities using vulnerability templates and store them inside reports of a project. SARF is prepared to be extended with in your own environment to satisfy your needs. 
Home-page: https://github.com/elchicodepython/SARF
Author: Samuel López Saura
Author-email: samuellopezsaura@gmail.com
License: MIT
Platform: UNKNOWN
Classifier: Programming Language :: Python :: 3
Classifier: License :: OSI Approved :: MIT License
Classifier: Operating System :: OS Independent
Requires-Dist: dependency-injector (<5.0,>=4.41)
Requires-Dist: awesome-messages (<2.0,>=1.0.0)
Requires-Dist: PyYAML (<7.0,>=6.0)
Requires-Dist: PyInquirer (<2.0,>=1.0.3)
Requires-Dist: datalift (<1.0,>=0.1.2)
Requires-Dist: sarf-simple-crud (<1.0,>=0.1.0)
